dbt_airflow/__init__.py
dbt_airflow/core/__init__.py
dbt_airflow/core/config.py
dbt_airflow/core/task.py
dbt_airflow/core/task_builder.py
dbt_airflow/core/task_group.py
dbt_airflow/core/task_list.py
dbt_airflow/exceptions.py
dbt_airflow/operators/base.py
dbt_airflow/operators/bash.py
dbt_airflow/operators/execution.py
dbt_airflow/operators/kubernetes.py
dbt_airflow/parser/__init__.py
dbt_airflow/parser/dbt.py
dbt_airflow-3.0.3.dist-info/METADATA
dbt_airflow-3.0.3.dist-info/WHEEL
dbt_airflow-3.0.3.dist-info/RECORD
