Metadata-Version: 2.4
Name: dbt-airflow
Version: 3.0.3
Summary: A Python package that creates fine-grained Airflow tasks for dbt
License: MIT
Author: Giorgos Myrianthous
Author-email: giorgos.myrianthous@gmail.com
Requires-Python: >=3.9.0,<4
Classifier: License :: OSI Approved :: MIT License
Classifier: Programming Language :: Python :: 3
Classifier: Programming Language :: Python :: 3.9
Classifier: Programming Language :: Python :: 3.10
Classifier: Programming Language :: Python :: 3.11
Classifier: Programming Language :: Python :: 3.12
Classifier: Programming Language :: Python :: 3.13
Classifier: Programming Language :: Python :: 3.14
Requires-Dist: apache-airflow (>=2.0.0,<3)
Requires-Dist: apache-airflow-providers-cncf-kubernetes (>=6.0.0)
Requires-Dist: dbt-core (>=1.9.0)
Requires-Dist: pydantic (>=2.0.0,<3)
Project-URL: Repository, https://github.com/gmyrianthous/dbt-airflow
